folder_dict/__init__.py
folder_dict-0.1.2.dist-info/LICENSE
folder_dict-0.1.2.dist-info/WHEEL
folder_dict-0.1.2.dist-info/METADATA
folder_dict-0.1.2.dist-info/RECORD
