Metadata-Version: 2.1
Name: folder-dict
Version: 0.1.2
Summary: TThe versatile dict for Python!
Home-page: https://github.com/Geson-anko/folder_dict
License: MIT
Author: Yasuhiro Shimomura
Author-email: 22shimoyasu22@gmail.com
Requires-Python: >=3.9,<4.0
Classifier: Intended Audience :: Developers
Classifier: License :: OSI Approved :: MIT License
Classifier: Operating System :: OS Independent
Classifier: Programming Language :: Python
Classifier: Programming Language :: Python :: 3
Classifier: Programming Language :: Python :: 3.10
Classifier: Programming Language :: Python :: 3.9
Classifier: Topic :: Software Development :: Libraries :: Python Modules
Requires-Dist: path-dict (>=1.2.1,<2.0.0)
Project-URL: Repository, https://github.com/Geson-anko/folder_dict
